django_nuit-1.2.2.dist-info/DESCRIPTION.rst
django_nuit-1.2.2.dist-info/METADATA
django_nuit-1.2.2.dist-info/RECORD
django_nuit-1.2.2.dist-info/WHEEL
django_nuit-1.2.2.dist-info/metadata.json
django_nuit-1.2.2.dist-info/top_level.txt
nuit/__init__.py
nuit/autoconfig.py
nuit/context_processors.py
nuit/handlers.py
nuit/models.py
nuit/utils.py
nuit/version.py
nuit/views.py
nuit/static/nuit.js
nuit/static/nuit.scss
nuit/static/nuit/_custom.scss
nuit/static/nuit/_foundation_overrides.scss
nuit/static/nuit/_mixins.scss
nuit/static/nuit/_styles.scss
nuit/static/nuit/_variables.scss
nuit/static/nuit/css/no-toggle-topbar.css
nuit/static/nuit/js/login.js
nuit/templates/nuit/base.html
nuit/templates/nuit/bases/_error_page.html
nuit/templates/nuit/generic/400.html
nuit/templates/nuit/generic/403.html
nuit/templates/nuit/generic/404.html
nuit/templates/nuit/generic/500.html
nuit/templates/nuit/generic/list.html
nuit/templates/nuit/generic/login.html
nuit/templates/nuit/includes/_application_menu.html
nuit/templates/nuit/includes/_form.html
nuit/templates/nuit/includes/_menu.html
nuit/templates/nuit/includes/_pagination_menu.html
nuit/templates/nuit/includes/_search_form.html
nuit/templates/nuit/includes/loader.html
nuit/templatetags/__init__.py
nuit/templatetags/nuit.py
nuit/tests/__init__.py
nuit/tests/forms.py
nuit/tests/test_main.py
nuit/tests/urls.py
nuit/tests/views.py
