Metadata-Version: 2.0
Name: django-nuit
Version: 1.2.2
Summary: Django Netnix User Interface Tools
Home-page: UNKNOWN
Author: Netnix Team
Author-email: netnix@ocado.com
License: UNKNOWN
Platform: UNKNOWN
Requires-Dist: asteval
Requires-Dist: django-foundation-statics (>=5.4.7-2)
Requires-Dist: django-jquery
Requires-Dist: django-foundation-icons (>=3.1)
Requires-Dist: django (<2.0)
Requires-Dist: django-autoconfig
Requires-Dist: django-bourbon
Requires-Dist: django-pipeline (>=1.6.0)
Requires-Dist: six
